aloy-0.2.0.dist-info/METADATA
aloy-0.2.0.dist-info/WHEEL
aloy-0.2.0.dist-info/license_files/LICENSE
aloy/guis/curses/curses_text.py
aloy/guis/curses/curses_window.py
aloy/guis/curses/__init__.py
aloy/guis/subjectlistener.py
aloy/guis/observable.py
aloy/guis/__init__.py
aloy/guis/examples/__init__.py
aloy/guis/examples/splash_screen.py
aloy/guis/examples/windows.py
aloy/guis/pubsub.py
aloy/guis/gui.py
aloy/guis/widgets/textwidgets.py
aloy/guis/widgets/__init__.py
aloy/guis/widgets/opencv.py
aloy/guis/widgets/buttons.py
aloy/guis/widgets/controlinterface.py
aloy/guis/widgets/placeholders.py
aloy/datastructures/sequences.py
aloy/datastructures/queues.py
aloy/datastructures/graph.py
aloy/datastructures/__init__.py
aloy/datastructures/disjointset.py
aloy/datastructures/mappings.py
aloy/datastructures/trees.py
aloy/datastructures/views.py
aloy/learning/reinforcement/tools.py
aloy/learning/reinforcement/__init__.py
aloy/learning/convolutional.py
aloy/learning/__init__.py
aloy/optimization/decayfunctions.py
aloy/optimization/swarmintelligence/particleswarm.ipynb
aloy/optimization/swarmintelligence/__init__.py
aloy/optimization/swarmintelligence/particleswarm.py
aloy/optimization/__init__.py
aloy/optimization/problems.py
aloy/optimization/evolutionary/geneticalgorithms.ipynb
aloy/optimization/evolutionary/__init__.py
aloy/optimization/evolutionary/geneticalgorithms.py
aloy/tests/control_tests/test_control.py
aloy/tests/unittests/test_disjointset.py
aloy/tests/unittests/test_graph.py
aloy/__init__.py
aloy/concurrency/synchronization.py
aloy/concurrency/__init__.py
aloy/concurrency/executors.py
aloy/concurrency/atomic.py
aloy/concurrency/clocks.py
aloy/datahandling/terminalplot.py
aloy/datahandling/__init__.py
aloy/datahandling/comparison.py
aloy/datahandling/runningstats.py
aloy/datahandling/makedata.py
aloy/robots/__init__.py
aloy/robots/robotcontrol.py
aloy/games/_game_errors.py
aloy/games/blockbreakergame.py
aloy/games/__init__.py
aloy/games/agents/snakeRL.py
aloy/games/agents/__init__.py
aloy/games/snakegame.py
aloy/games/gamerecorder.py
aloy/games/pacmangame.py
aloy-0.2.0.dist-info/RECORD
