Metadata-Version: 2.1
Name: aloy
Version: 0.2.0
Classifier: Development Status :: 1 - Planning
Classifier: Intended Audience :: Developers
Classifier: Intended Audience :: Education
Classifier: Intended Audience :: Science/Research
Classifier: Natural Language :: English
Classifier: Natural Language :: Chinese (Simplified)
Classifier: License :: OSI Approved :: GNU General Public License v3 (GPLv3)
Classifier: Operating System :: OS Independent
Classifier: Programming Language :: Rust
Classifier: Programming Language :: Python
Classifier: Programming Language :: Python :: 3
Classifier: Programming Language :: Python :: 3.11
Classifier: Programming Language :: Python :: Implementation :: CPython
Classifier: Programming Language :: Python :: Implementation :: PyPy
Classifier: Topic :: Software Development :: Libraries
Classifier: Topic :: Software Development :: Libraries :: Python Modules
Classifier: Typing :: Typed
Requires-Dist: numpy ==1.24.3
Requires-Dist: pyside6 ==6.5.2
Requires-Dist: pyside6-addons ==6.5.2
Requires-Dist: pyside6-essentials ==6.5.2
Requires-Dist: scikit-learn ==1.2.2
Requires-Dist: scipy ==1.10.1
Requires-Dist: networkx ==3.1
Requires-Dist: matplotlib ==3.7.1
Requires-Dist: networkx ==3.1
Requires-Dist: numba ==0.57.0
Requires-Dist: pandas ==1.5.3
Requires-Dist: psutil ==5.9.0
Requires-Dist: pyfiglet ==0.8.post1
Requires-Dist: scikit_learn ==1.2.2
Requires-Dist: tqdm ==4.65.0
Requires-Dist: typing_extensions ==4.8.0
Requires-Dist: torch ==2.1.0
Requires-Dist: gymnasium ==0.28.1
License-File: LICENSE
Summary: A Python package containing algorithms and data structures for AI, ML, and Robotics.
Keywords: aloy,algorithms,data structures,ai,ml,robotics
Author-email: Ollie Kampo <olliekampo@gmail.com>
Maintainer-email: Ollie Kampo <olliekampo@gmail.com>
Requires-Python: >=3.11
